cracknuts/__init__.py
cracknuts/__main__.py
cracknuts/logger.py
cracknuts/acquisition/__init__.py
cracknuts/acquisition/acquisition.py
cracknuts/cracker/__init__.py
cracknuts/cracker/cracker_basic.py
cracknuts/cracker/cracker_g1.py
cracknuts/cracker/cracker_s1.py
cracknuts/cracker/operator.py
cracknuts/cracker/protocol.py
cracknuts/cracker/serial.py
cracknuts/firmware/bs-cracker_s1_v0.1-0.1.0-alpha.12.bit.bin
cracknuts/firmware/map.json
cracknuts/firmware/server-0.5.6-alpha.3.bin
cracknuts/firmware/server-sd-0.5.6-alpha.3.bin
cracknuts/jupyter/__init__.py
cracknuts/jupyter/acquisition_panel.py
cracknuts/jupyter/cracker_s1_panel.py
cracknuts/jupyter/cracknuts_panel.py
cracknuts/jupyter/panel.py
cracknuts/jupyter/scope_panel.py
cracknuts/jupyter/trace_panel.py
cracknuts/jupyter/ui_sync.py
cracknuts/jupyter/static/AcquisitionPanelWidget.js
cracknuts/jupyter/static/CrackNutsPanelWidget.js
cracknuts/jupyter/static/CrackerS1PanelWidget.js
cracknuts/jupyter/static/ScopePanelWidget.js
cracknuts/jupyter/static/TracePanelWidget.css
cracknuts/jupyter/static/TracePanelWidget.js
cracknuts/mock/__init__.py
cracknuts/mock/mock_cracker.py
cracknuts/mock/mock_operator.py
cracknuts/scope/__init__.py
cracknuts/scope/scope_acquisition.py
cracknuts/template/READEM.md
cracknuts/trace/__init__.py
cracknuts/trace/trace.py
cracknuts/tutorials/requirements.txt
cracknuts/tutorials/Basic/Lab1_Setup.ipynb
cracknuts/tutorials/Basic/Lab3_Acquisition.ipynb
cracknuts/tutorials/Basic/Lab4_CPA.ipynb
cracknuts/tutorials/Basic/trace-acquisition.ipynb
cracknuts/tutorials/Basic/attatchments/CrackerXX-DC-Adapter-Direct-Connect.svg
cracknuts/tutorials/Basic/attatchments/CrackerXX-DC-Adapter.svg
cracknuts/tutorials/Basic/attatchments/CrackerXX-PoE-Adapter-Direct-Connect.svg
cracknuts/tutorials/Basic/attatchments/CrackerXX-PoE-Adapter-Wireless-Connect.svg
cracknuts/tutorials/Basic/attatchments/CrackerXX-PoE-Adapter.svg
cracknuts/tutorials/Basic/attatchments/CrackerXX-PoE-Switch-Connect.svg
cracknuts-0.19.7.dist-info/licenses/LICENSE
cracknuts-0.19.7.dist-info/licenses/NOTICE
cracknuts-0.19.7.dist-info/METADATA
cracknuts-0.19.7.dist-info/WHEEL
cracknuts-0.19.7.dist-info/entry_points.txt
cracknuts-0.19.7.dist-info/top_level.txt
cracknuts-0.19.7.dist-info/RECORD
