Metadata-Version: 2.4
Name: cracknuts
Version: 0.19.7
Summary: A library for cracknuts device.
Author-email: Dingzb <dingzibiao@gmail.com>
Maintainer-email: Dingzb <dingzibiao@gmail.com>
License: 
Project-URL: homepage, https://cracknuts.io
Requires-Python: >=3.12
License-File: LICENSE
License-File: NOTICE
Requires-Dist: numpy~=1.26.4
Requires-Dist: click~=8.1.7
Requires-Dist: zarr~=2.18.2
Requires-Dist: packaging~=24.1
Requires-Dist: anywidget~=0.9.13
Provides-Extra: jupyter
Requires-Dist: jupyter~=1.1.1; extra == "jupyter"
Requires-Dist: ipykernel~=6.30.1; extra == "jupyter"
Dynamic: license-file
